odoo/addons/purchase_order_weight_volume/README.rst
odoo/addons/purchase_order_weight_volume/__init__.py
odoo/addons/purchase_order_weight_volume/__manifest__.py
odoo/addons/purchase_order_weight_volume/i18n/it.po
odoo/addons/purchase_order_weight_volume/i18n/purchase_order_weight_volume.pot
odoo/addons/purchase_order_weight_volume/models/__init__.py
odoo/addons/purchase_order_weight_volume/models/purchase_order.py
odoo/addons/purchase_order_weight_volume/models/res_company.py
odoo/addons/purchase_order_weight_volume/models/res_config_settings.py
odoo/addons/purchase_order_weight_volume/readme/CONTRIBUTORS.rst
odoo/addons/purchase_order_weight_volume/readme/DESCRIPTION.rst
odoo/addons/purchase_order_weight_volume/readme/USAGE.rst
odoo/addons/purchase_order_weight_volume/report/purchase_report_templates.xml
odoo/addons/purchase_order_weight_volume/static/description/icon.png
odoo/addons/purchase_order_weight_volume/static/description/index.html
odoo/addons/purchase_order_weight_volume/views/purchase_order_view.xml
odoo/addons/purchase_order_weight_volume/views/res_config_settings_views.xml
odoo14_addon_purchase_order_weight_volume-14.0.1.0.1.dist-info/METADATA
odoo14_addon_purchase_order_weight_volume-14.0.1.0.1.dist-info/WHEEL
odoo14_addon_purchase_order_weight_volume-14.0.1.0.1.dist-info/top_level.txt
odoo14_addon_purchase_order_weight_volume-14.0.1.0.1.dist-info/RECORD
